p2g/VERSION
p2g/__init__.py
p2g/__main__.py
p2g/axis.py
p2g/builtin.py
p2g/coords.py
p2g/docs/coverage.svg
p2g/docs/haas.txt
p2g/docs/howto.md
p2g/docs/howto.txt
p2g/docs/mit.svg
p2g/docs/pytest.svg
p2g/err.py
p2g/examples/maxflutes.nc
p2g/examples/maxflutes.py
p2g/examples/probecalibrate.nc
p2g/examples/probecalibrate.py
p2g/examples/usrlib.py
p2g/examples/vicecenter.nc
p2g/examples/vicecenter.py
p2g/fstring.py
p2g/gbl.py
p2g/goto.py
p2g/haas.py
p2g/main.py
p2g/nd.py
p2g/op.py
p2g/scalar.py
p2g/stat.py
p2g/symbol.py
p2g/sys.py
p2g/vector.py
p2g/walkbase.py
p2g/walkexpr.py
p2g/walkfunc.py
p2g/walkstat.py
p2g-0.3.10.dist-info/METADATA
p2g-0.3.10.dist-info/WHEEL
p2g-0.3.10.dist-info/entry_points.txt
p2g-0.3.10.dist-info/RECORD
