Metadata-Version: 2.1
Name: p2g
Version: 0.3.10
Summary: Transpile python into cnc gcode.
Home-page: https://github.com/0x5ac/p2g
License: MIT
Keywords: cnc,gcode,mill,haas,g-code,probe,vf
Author: sac
Author-email: sac@0x5ac.com
Requires-Python: >=3.10,<4.0
Classifier: Development Status :: 3 - Alpha
Classifier: Intended Audience :: Manufacturing
Classifier: Intended Audience :: Other Audience
Classifier: License :: OSI Approved :: MIT License
Classifier: Programming Language :: Python
Classifier: Programming Language :: Python :: 3
Classifier: Programming Language :: Python :: 3.10
Classifier: Programming Language :: Python :: 3.11
Classifier: Topic :: Software Development :: Compilers
Requires-Dist: docopt (>=0.6.2,<0.7.0)
Requires-Dist: typeguard (>=3.0.2,<4.0.0)
Project-URL: Repository, https://github.com/0x5ac/p2g
